Metadata-Version: 2.4
Name: datax-py
Version: 1.0.0
Summary: Advanced Data Analytics Package with cleaning, statistics, and visualization
Author-email: Amirbek Azimov <amirbekazimov7@gmail.com>
Maintainer-email: Amirbek Azimov <amirbekazimov7@gmail.com>
License: MIT
Project-URL: Homepage, https://github.com/amirbekazimov/datax-py
Project-URL: Documentation, https://datax-py.readthedocs.io
Project-URL: Repository, https://github.com/amirbekazimov/datax-py.git
Project-URL: Bug Tracker, https://github.com/amirbekazimov/datax-py/issues
Project-URL: Source Code, https://github.com/amirbekazimov/datax-py
Project-URL: Download, https://github.com/amirbekazimov/datax-py/archive/v1.0.0.tar.gz
Keywords: data,analytics,cleaning,statistics,visualization,cli,machine learning
Classifier: Development Status :: 5 - Production/Stable
Classifier: Intended Audience :: Developers
Classifier: Intended Audience :: Science/Research
Classifier: License :: OSI Approved :: MIT License
Classifier: Operating System :: OS Independent
Classifier: Programming Language :: Python :: 3
Classifier: Programming Language :: Python :: 3.8
Classifier: Programming Language :: Python :: 3.9
Classifier: Programming Language :: Python :: 3.10
Classifier: Programming Language :: Python :: 3.11
Classifier: Programming Language :: Python :: 3.12
Classifier: Topic :: Scientific/Engineering :: Information Analysis
Classifier: Topic :: Software Development :: Libraries :: Python Modules
Classifier: Topic :: Scientific/Engineering :: Mathematics
Classifier: Topic :: Scientific/Engineering :: Visualization
Requires-Python: >=3.8
License-File: LICENSE
Requires-Dist: pandas>=1.3.0
Requires-Dist: numpy>=1.21.0
Requires-Dist: matplotlib>=3.5.0
Requires-Dist: seaborn>=0.11.0
Requires-Dist: scipy>=1.7.0
Requires-Dist: scikit-learn>=1.0.0
Requires-Dist: plotly>=5.0.0
Requires-Dist: openpyxl>=3.0.0
Requires-Dist: pyarrow>=5.0.0
Provides-Extra: dev
Requires-Dist: pytest>=6.0.0; extra == "dev"
Requires-Dist: pytest-cov>=2.12.0; extra == "dev"
Requires-Dist: pytest-mock>=3.6.0; extra == "dev"
Requires-Dist: black>=21.0.0; extra == "dev"
Requires-Dist: flake8>=3.9.0; extra == "dev"
Requires-Dist: mypy>=0.910; extra == "dev"
Requires-Dist: isort>=5.9.0; extra == "dev"
Requires-Dist: pre-commit>=2.15.0; extra == "dev"
Provides-Extra: docs
Requires-Dist: sphinx>=4.0.0; extra == "docs"
Requires-Dist: sphinx-rtd-theme>=1.0.0; extra == "docs"
Requires-Dist: myst-parser>=0.15.0; extra == "docs"
Requires-Dist: sphinx-autodoc-typehints>=1.12.0; extra == "docs"
Provides-Extra: jupyter
Requires-Dist: jupyter>=1.0.0; extra == "jupyter"
Requires-Dist: ipywidgets>=7.6.0; extra == "jupyter"
Requires-Dist: notebook>=6.4.0; extra == "jupyter"
Provides-Extra: all
Requires-Dist: datax[dev,docs,jupyter]; extra == "all"
Dynamic: license-file
